fast_rabbit/__init__.py
fast_rabbit/channel_manager.py
fast_rabbit/connection_manager.py
fast_rabbit/consumer_error_handler.py
fast_rabbit/consumer_manager.py
fast_rabbit/fast_rabbit.py
fast_rabbit/fast_rabbit_router.py
fast_rabbit/logger_config.py
fast_rabbit/message_publisher.py
fast_rabbit/utils.py
tests/__init__.py
tests/test_basic_plublish_consumer.py
tests/test_multiple_messages.py
tests/test_pydantic_models.py
tests/test_routing.py
fast_rabbit-0.1.18.dist-info/LICENSE
fast_rabbit-0.1.18.dist-info/METADATA
fast_rabbit-0.1.18.dist-info/WHEEL
fast_rabbit-0.1.18.dist-info/top_level.txt
fast_rabbit-0.1.18.dist-info/RECORD
