Metadata-Version: 2.1
Name: fast-rabbit
Version: 0.1.18
Summary: An asynchronous RabbitMQ client for Python
Home-page: https://github.com/shaunbarney/fast_rabbit
Author: Shaun James Barney
Author-email: shaunbarney@outlook.com
License: UNKNOWN
Platform: UNKNOWN
Classifier: Programming Language :: Python :: 3
Classifier: License :: OSI Approved :: MIT License
Classifier: Operating System :: OS Independent
Requires-Python: >=3.9
License-File: LICENSE
Requires-Dist: aio-pika
Requires-Dist: aiormq
Requires-Dist: idna
Requires-Dist: multidict
Requires-Dist: pamqp
Requires-Dist: yarl
Requires-Dist: asyncio
Requires-Dist: pydantic
